ninja_fsbr.py
django_ninja_fsbr-0.2.1.dist-info/LICENSE
django_ninja_fsbr-0.2.1.dist-info/WHEEL
django_ninja_fsbr-0.2.1.dist-info/METADATA
django_ninja_fsbr-0.2.1.dist-info/RECORD
